README.md
setup.py
sol3rd/__init__.py
sol3rd/__version__.py
sol3rd/sol3rd.py
sol3rd.egg-info/PKG-INFO
sol3rd.egg-info/SOURCES.txt
sol3rd.egg-info/dependency_links.txt
sol3rd.egg-info/entry_points.txt
sol3rd.egg-info/requires.txt
sol3rd.egg-info/top_level.txt