Metadata-Version: 2.1
Name: sol3rd
Version: 0.3
Summary: Install 3rd party apps in Solus or upgrade them
Home-page: UNKNOWN
Author: armandg
Author-email: armandg@gmail.com
License: GPL-v3.0
Platform: UNKNOWN
